{
  "enableSearch": true,
  "pages": [
    {
      "title": "Forum Activities Dashboard",
      "pageNav": 4,
      "src": "contents/forum-activities.md",
      "layout": "default",
      "headings": {
        "forum-activities-dashboard": "Forum activities dashboard"
      },
      "headingKeywords": {}
    },
    {
      "title": "iP review comments dashboard",
      "pageNav": 4,
      "src": "contents/ip-comments.md",
      "layout": "default",
      "headings": {
        "ip-review-comments-dashboard": "iP review comments dashboard"
      },
      "headingKeywords": {}
    },
    {
      "title": "iP progress dashboard",
      "src": "contents/ip-progress.md",
      "layout": "default",
      "headings": {
        "ip-progress-dashboard": "iP progress dashboard"
      },
      "headingKeywords": {}
    },
    {
      "title": "Participation dashboard",
      "src": "contents/participation.md",
      "layout": "default",
      "headings": {
        "participation-dashboard": "Participation dashboard"
      },
      "headingKeywords": {}
    },
    {
      "src": "contents/projectGrading.md",
      "title": "",
      "layout": "default",
      "headings": {
        "cs2113t-m16-1": "CS2113T-M16-1",
        "cs2113t-m16-1-2": "CS2113T-M16-1",
        "cs2113t-m16-2": "CS2113T-M16-2",
        "cs2113t-m16-2-2": "CS2113T-M16-2",
        "cs2113t-t12-1": "CS2113T-T12-1",
        "cs2113t-t12-1-2": "CS2113T-T12-1",
        "cs2113t-t12-2": "CS2113T-T12-2",
        "cs2113t-t12-2-2": "CS2113T-T12-2",
        "cs2113t-t12-3": "CS2113T-T12-3",
        "cs2113t-t12-3-2": "CS2113T-T12-3",
        "cs2113t-t12-4": "CS2113T-T12-4",
        "cs2113t-t12-4-2": "CS2113T-T12-4",
        "cs2113t-t13-1": "CS2113T-T13-1",
        "cs2113t-t13-1-2": "CS2113T-T13-1",
        "cs2113t-t13-2": "CS2113T-T13-2",
        "cs2113t-t13-2-2": "CS2113T-T13-2",
        "cs2113t-t13-3": "CS2113T-T13-3",
        "cs2113t-t13-3-2": "CS2113T-T13-3",
        "cs2113-t14-1": "CS2113-T14-1",
        "cs2113-t14-1-2": "CS2113-T14-1",
        "cs2113-t14-2": "CS2113-T14-2",
        "cs2113-t14-2-2": "CS2113-T14-2",
        "cs2113-t14-3": "CS2113-T14-3",
        "cs2113-t14-3-2": "CS2113-T14-3",
        "cs2113-t14-4": "CS2113-T14-4",
        "cs2113-t14-4-2": "CS2113-T14-4",
        "cs2113-t15-1": "CS2113-T15-1",
        "cs2113-t15-1-2": "CS2113-T15-1",
        "cs2113-t15-2": "CS2113-T15-2",
        "cs2113-t15-2-2": "CS2113-T15-2",
        "cs2113-t15-3": "CS2113-T15-3",
        "cs2113-t15-3-2": "CS2113-T15-3",
        "cs2113-t15-4": "CS2113-T15-4",
        "cs2113-t15-4-2": "CS2113-T15-4"
      },
      "headingKeywords": {}
    },
    {
      "title": "tP comments dashboard",
      "pageNav": 4,
      "src": "contents/tp-comments.md",
      "layout": "default",
      "headings": {
        "1-tay-jun-wen-tototto-1-comments": "1. TAY JUN WEN @tototto (1 comments)",
        "2-januarius-jang-kheng-lim-januariusjang-0-comments": "2. JANUARIUS JANG KHENG LIM @JanuariusJang (0 comments)",
        "3-chi-lai-ping-chilaiping-0-comments": "3. CHI LAI PING @Chilaiping (0 comments)",
        "4-chan-weizhong-e0260222-0-comments": "4. CHAN WEIZHONG @e0260222 (0 comments)",
        "5-olivier-cheah-kun-da-skyventus-0-comments": "5. OLIVIER CHEAH KUN DA @skyventus (0 comments)",
        "6-lin-tong-dgc5213-0-comments": "6. LIN TONG @dgc5213 (0 comments)",
        "7-hngoi-zi-wen-e0261618-0-comments": "7. HNGOI ZI WEN @e0261618 (0 comments)",
        "8-adi-kesava-das-s-o-sudarsana-dasa-adhikari-adi-kd0021-0-comments": "8. ADI KESAVA DAS S/O SUDARSANA DASA ADHIKARI @adi-kd0021 (0 comments)",
        "9-lin-binhui-binbinhui-0-comments": "9. LIN BINHUI @binbinhui (0 comments)",
        "10-lin-qing-linqing42-0-comments": "10. LIN QING @linqing42 (0 comments)",
        "11-zheng-shijie-zhengshijienus-0-comments": "11. ZHENG SHIJIE @ZhengShijieNUS (0 comments)",
        "12-hong-jiancheng-pigoliver-0-comments": "12. HONG JIANCHENG @pigoliver (0 comments)",
        "tp-comments-dashboard": "tP comments dashboard"
      },
      "headingKeywords": {}
    },
    {
      "title": "tP progress dashboard",
      "src": "contents/tp-progress.md",
      "layout": "default",
      "headings": {
        "tp-progress-dashboard": "tP progress dashboard"
      },
      "headingKeywords": {}
    },
    {
      "title": "dashboards",
      "src": "index.md",
      "layout": "default",
      "headings": {
        "tic4001-dashboards": "TIC4001 dashboards"
      },
      "headingKeywords": {}
    }
  ]
}
